mycalc/mycalc.py
KJOCalcmc-0.0.1.dist-info/LICENSE
KJOCalcmc-0.0.1.dist-info/METADATA
KJOCalcmc-0.0.1.dist-info/WHEEL
KJOCalcmc-0.0.1.dist-info/top_level.txt
KJOCalcmc-0.0.1.dist-info/RECORD
