Metadata-Version: 2.1
Name: KJOCalcmc
Version: 0.0.1
Summary: oss dev my calculator 0001
Home-page: https://github.com/chunsejin/calc0001/
Download-URL: https://github.com/chunsejin/calc0001/
Author: sjchun
Classifier: Programming Language :: Python :: 3
License-File: LICENSE
